{
  "_meta": {
    "version": "1.0.0",
    "updatedAt": "2026-04-27",
    "description": "SW Design System Guide 사이트 네비게이션 구조"
  },
  "nav": [
    {
      "group": "개요",
      "items": [
        {
          "id": "index",
          "title": "Overview",
          "icon": "🏠",
          "href": "index.html",
          "status": "ready",
          "description": "디자인시스템 소개, 통계, 로드맵"
        }
      ]
    },
    {
      "group": "Foundation",
      "items": [
        {
          "id": "foundation",
          "title": "Foundation Tokens",
          "icon": "🎨",
          "href": "pages/foundation.html",
          "status": "ready",
          "description": "Primitive 색상 팔레트, Semantic 토큰, 타이포그래피",
          "sections": [
            "Primitive Colors — Brand + 11 Palettes",
            "Semantic Colors — Background / Text / Border / Icon / Action / State",
            "Typography — Title Base / Body Base + Font Weights",
            "Coming Soon — Spacing, Radius, Shadow, Motion"
          ]
        },
        {
          "id": "semantic",
          "title": "Semantic Tokens",
          "icon": "🌗",
          "href": "pages/semantic.html",
          "status": "soon",
          "description": "역할 기반 토큰, Light/Dark 테마 전환 구조"
        }
      ]
    },
    {
      "group": "Design System",
      "items": [
        {
          "id": "components",
          "title": "Components",
          "icon": "🧩",
          "href": "pages/components.html",
          "status": "soon",
          "description": "Core / Domain / Legacy 컴포넌트 라이브러리"
        },
        {
          "id": "patterns",
          "title": "Patterns",
          "icon": "📐",
          "href": "pages/patterns.html",
          "status": "soon",
          "description": "Search+Table, Tree+Detail 등 반복 레이아웃 패턴"
        },
        {
          "id": "policy",
          "title": "Policy",
          "icon": "📋",
          "href": "pages/policy.html",
          "status": "wip",
          "description": "토큰 사용 원칙, 신규/레거시 기준, 다크모드 대응 정책"
        },
        {
          "id": "legacy",
          "title": "Legacy Guide",
          "icon": "🗂️",
          "href": "pages/legacy.html",
          "status": "soon",
          "description": "구버전 토큰 → 신규 토큰 마이그레이션 가이드"
        }
      ]
    },
    {
      "group": "AI 워크플로우",
      "items": [
        {
          "id": "guide-md",
          "title": "Guide MD",
          "icon": "📋",
          "href": "pages/guide-md.html",
          "status": "ready",
          "description": "Semantic · Component Token 정의서 — 복사 가능한 원본 Markdown"
        },
        {
          "id": "md-review",
          "title": "MD 리뷰",
          "icon": "🔍",
          "href": "pages/md-review.html",
          "status": "ready",
          "description": "수정 제안 · 결정 대기 항목 · Figma 작업 체크리스트"
        }
      ]
    }
  ],
  "statusLegend": {
    "ready": "완료",
    "wip": "작성 중",
    "soon": "Coming Soon",
    "new": "신규"
  }
}
