{
  "meta": {
    "name": "S1 UX Guide 2.4 Figma Variable Usage",
    "version": "0.1.0",
    "status": "partial",
    "source": "figma-mcp-audit",
    "scannedAt": "2026-05-19",
    "fileKey": "yE5UCFEbmXJBlYJWB24Lz2",
    "fileName": "S1 UX Design Guide V2.4 (Figma)",
    "method": "mcp:get_variable_defs + mcp:get_design_context",
    "note": "MCP를 통해 접근 가능한 노드만 스캔됨. boundVariables 직접 추출 불가 — MCP는 노드별 사용 variable 목록만 반환. property-level binding(fill/stroke/text)은 design_context Tailwind class 위치로 inferredRole을 추정함. 전체 파일 스캔 및 정확한 property binding 추출은 Plugin Export 필요.",
    "limitations": [
      "MCP get_variable_defs는 노드에 사용된 variable 이름과 resolved value만 반환. 어떤 property에 bound되었는지 직접 표시하지 않음.",
      "inferredRole은 variable 이름 패턴 + design_context 코드 위치로 추정한 값임. boundVariables[]의 1:1 매핑이 아님.",
      "Cover 페이지 외 component master 페이지 메타데이터 접근 불가 — known nodeId로 점접근(spot access)만 가능.",
      "Mode별 값(light/dark) 비교 불가 — MCP는 현재 활성 mode 값만 반환."
    ]
  },
  "scannedNodes": [
    {
      "nodeId": "540:3794",
      "nodeName": "datepicker_input / form-control",
      "nodeType": "componentSet",
      "accessStatus": "ok",
      "variableCount": 24
    },
    {
      "nodeId": "540:4501",
      "nodeName": "button-primary (PC button)",
      "nodeType": "component",
      "accessStatus": "ok",
      "variableCount": 9
    },
    {
      "nodeId": "540:4502",
      "nodeName": "button-primary label",
      "nodeType": "textNode",
      "accessStatus": "ok",
      "variableCount": 2
    },
    {
      "nodeId": "540:3836",
      "nodeName": "datepicker_mobile bottomsheet",
      "nodeType": "frame",
      "accessStatus": "ok",
      "variableCount": 36
    },
    {
      "nodeId": "6456:4033",
      "nodeName": "DatePicker Section 2 (composite)",
      "nodeType": "frame",
      "accessStatus": "ok",
      "variableCount": 53
    },
    {
      "nodeId": "540:7663",
      "nodeName": "Style Guide root frame",
      "nodeType": "frame",
      "accessStatus": "ok",
      "variableCount": 48
    },
    {
      "nodeId": "540:7368",
      "nodeName": "Typography style frame",
      "nodeType": "frame",
      "accessStatus": "ok",
      "variableCount": 11
    },
    {
      "nodeId": "540:7665",
      "nodeName": "Style Guide child node",
      "nodeType": "node",
      "accessStatus": "ok",
      "variableCount": 2
    },
    {
      "nodeId": "6443:4408",
      "nodeName": "Login input frame",
      "nodeType": "frame",
      "accessStatus": "failed",
      "error": "invalid node — Figma Debug UUID 57f814a0"
    },
    {
      "nodeId": "6443:4655",
      "nodeName": "DatePicker component (HD candidate)",
      "nodeType": "componentSet",
      "accessStatus": "failed",
      "error": "invalid node — Figma Debug UUID 0b52f46d"
    },
    {
      "nodeId": "6443:4606",
      "nodeName": "TimePicker component (HD candidate)",
      "nodeType": "componentSet",
      "accessStatus": "failed",
      "error": "invalid node — Figma Debug UUID 40f7e142"
    }
  ],
  "components": [
    {
      "nodeId": "540:3794",
      "nodeName": "datepicker_input / form-control",
      "componentRole": "form-control (Input, Select, DatePicker trigger 공용)",
      "usedVariables": [
        { "name": "color/form-control/bg/default", "value": "#ffffff", "inferredRole": "background" },
        { "name": "color/form-control/bg/disabled", "value": "#f5f5f5", "inferredRole": "background" },
        { "name": "color/form-control/border/default", "value": "#d9d9d9", "inferredRole": "border" },
        { "name": "color/form-control/border/selected", "value": "#1d6ceb", "inferredRole": "border" },
        { "name": "color/form-control/border/disabled", "value": "#d9d9d9", "inferredRole": "border" },
        { "name": "color/form-control/text/default", "value": "#353535", "inferredRole": "text" },
        { "name": "color/form-control/text/placeholder", "value": "#757575", "inferredRole": "text" },
        { "name": "color/form-control/text/disabled", "value": "#c4c4c4", "inferredRole": "text" },
        { "name": "color/icon/gray-dark", "value": "#353535", "inferredRole": "icon" },
        { "name": "color/icon/gray-light", "value": "#c4c4c4", "inferredRole": "icon" },
        { "name": "sizing/form-control/height/md", "value": "44", "inferredRole": "sizing" },
        { "name": "sizing/form-control/height/lg", "value": "48", "inferredRole": "sizing" },
        { "name": "sizing/form-control/height/xs", "value": "34", "inferredRole": "sizing" },
        { "name": "sizing/form-control/height/xxs", "value": "28", "inferredRole": "sizing" },
        { "name": "radius/control/sm", "value": "4", "inferredRole": "radius" },
        { "name": "radius/4", "value": "4", "inferredRole": "radius" },
        { "name": "border-width/default", "value": "1", "inferredRole": "border-width" },
        { "name": "spacing/padding/inline/sm", "value": "16", "inferredRole": "spacing" },
        { "name": "spacing/padding/inline/xs", "value": "12", "inferredRole": "spacing" },
        { "name": "spacing/padding/inline/xxs", "value": "8", "inferredRole": "spacing" },
        { "name": "spacing/padding/block/xxs", "value": "8", "inferredRole": "spacing" },
        { "name": "spacing/4", "value": "4", "inferredRole": "spacing" },
        { "name": "component/control/text/14R", "value": "Pretendard 14 Regular", "inferredRole": "typography" },
        { "name": "component/control/label/12R", "value": "Pretendard 12 Regular", "inferredRole": "typography" }
      ]
    },
    {
      "nodeId": "540:4501",
      "nodeName": "button-primary (PC button)",
      "componentRole": "button - primary variant",
      "usedVariables": [
        { "name": "color/button/bg/primary--default", "value": "#1d6ceb", "inferredRole": "background" },
        { "name": "color/button/border/primary--default", "value": "#1d6ceb", "inferredRole": "border" },
        { "name": "color/button/label/primary--default", "value": "#ffffff", "inferredRole": "text" },
        { "name": "sizing/button/height/md", "value": "44", "inferredRole": "sizing" },
        { "name": "radius/4", "value": "4", "inferredRole": "radius" },
        { "name": "border-width/default", "value": "1", "inferredRole": "border-width" },
        { "name": "spacing/padding/inline/sm", "value": "16", "inferredRole": "spacing" },
        { "name": "spacing/padding/block/xs", "value": "12", "inferredRole": "spacing" },
        { "name": "component/button/label/14M", "value": "Pretendard 14 Medium", "inferredRole": "typography" }
      ]
    },
    {
      "nodeId": "540:3836",
      "nodeName": "datepicker_mobile bottomsheet",
      "componentRole": "DatePicker mobile panel",
      "usedVariables": [
        { "name": "color/text/title/primary", "value": "#000000", "inferredRole": "text" },
        { "name": "color/text/body/primary", "value": "#353535", "inferredRole": "text" },
        { "name": "color/text/body/tertiary", "value": "#757575", "inferredRole": "text" },
        { "name": "color/text/state/disabled", "value": "#c4c4c4", "inferredRole": "text" },
        { "name": "color/text/state/accent", "value": "#1d6ceb", "inferredRole": "text" },
        { "name": "color/text/state/accent-alt", "value": "#ffffff", "inferredRole": "text" },
        { "name": "color/icon/gray-dark", "value": "#353535", "inferredRole": "icon" },
        { "name": "color/control/bg/default", "value": "#ffffff", "inferredRole": "background" },
        { "name": "color/control/bg/selected", "value": "#1d6ceb", "inferredRole": "background" },
        { "name": "color/control/bg/selected-alt", "value": "#ffffff", "inferredRole": "background" },
        { "name": "color/control/border/selected", "value": "#1d6ceb", "inferredRole": "border" },
        { "name": "color/blue/50", "value": "#e2f1ff", "inferredRole": "background-range" },
        { "name": "color/base/white", "value": "#ffffff", "inferredRole": "background" },
        { "name": "surface/neutral/bg/base", "value": "#ffffff", "inferredRole": "background" },
        { "name": "color/button/bg/primary--default", "value": "#1d6ceb", "inferredRole": "background" },
        { "name": "color/button/border/primary--default", "value": "#1d6ceb", "inferredRole": "border" },
        { "name": "color/button/label/primary--default", "value": "#ffffff", "inferredRole": "text" },
        { "name": "sizing/icon/24", "value": "24", "inferredRole": "sizing" },
        { "name": "sizing/24", "value": "24", "inferredRole": "sizing" },
        { "name": "sizing/30", "value": "30", "inferredRole": "sizing" },
        { "name": "sizing/44", "value": "44", "inferredRole": "sizing" },
        { "name": "radius/full", "value": "999", "inferredRole": "radius" },
        { "name": "radius/4", "value": "4", "inferredRole": "radius" },
        { "name": "border-width/default", "value": "1", "inferredRole": "border-width" },
        { "name": "border-width/100", "value": "1", "inferredRole": "border-width" },
        { "name": "spacing/padding/inline/md", "value": "20", "inferredRole": "spacing" },
        { "name": "spacing/padding/inline/sm", "value": "16", "inferredRole": "spacing" },
        { "name": "spacing/padding/inline/lg", "value": "24", "inferredRole": "spacing" },
        { "name": "spacing/padding/block/sm", "value": "16", "inferredRole": "spacing" },
        { "name": "spacing/padding/block/md", "value": "20", "inferredRole": "spacing" },
        { "name": "spacing/section/xs", "value": "16", "inferredRole": "spacing" },
        { "name": "spacing/section/lg", "value": "32", "inferredRole": "spacing" },
        { "name": "title/20B", "value": "Pretendard 20 Bold", "inferredRole": "typography" },
        { "name": "title/24B", "value": "Pretendard 24 Bold", "inferredRole": "typography" },
        { "name": "title/16M", "value": "Pretendard 16 Medium", "inferredRole": "typography" },
        { "name": "Title/16M", "value": "Pretendard 16 Medium (alias)", "inferredRole": "typography" },
        { "name": "component/button/label/16M", "value": "Pretendard 16 Medium", "inferredRole": "typography" }
      ]
    },
    {
      "nodeId": "6456:4033",
      "nodeName": "DatePicker Section 2 (full composite — input + panel + nav)",
      "componentRole": "DatePicker section showing trigger input + calendar panel",
      "usedVariables": [
        { "name": "color/form-control/bg/default", "value": "#ffffff", "inferredRole": "background" },
        { "name": "color/form-control/bg/disabled", "value": "#f5f5f5", "inferredRole": "background" },
        { "name": "color/form-control/border/default", "value": "#d9d9d9", "inferredRole": "border" },
        { "name": "color/form-control/border/selected", "value": "#1d6ceb", "inferredRole": "border" },
        { "name": "color/form-control/border/disabled", "value": "#d9d9d9", "inferredRole": "border" },
        { "name": "color/form-control/text/default", "value": "#353535", "inferredRole": "text" },
        { "name": "color/form-control/text/placeholder", "value": "#757575", "inferredRole": "text" },
        { "name": "color/form-control/text/disabled", "value": "#c4c4c4", "inferredRole": "text" },
        { "name": "color/text/title/primary", "value": "#000000", "inferredRole": "text" },
        { "name": "color/text/body/primary", "value": "#353535", "inferredRole": "text" },
        { "name": "color/text/body/tertiary", "value": "#757575", "inferredRole": "text" },
        { "name": "color/text/state/disabled", "value": "#c4c4c4", "inferredRole": "text" },
        { "name": "color/text/state/accent", "value": "#1d6ceb", "inferredRole": "text" },
        { "name": "color/text/state/accent-alt", "value": "#ffffff", "inferredRole": "text" },
        { "name": "color/icon/gray-dark", "value": "#353535", "inferredRole": "icon" },
        { "name": "color/icon/gray-light", "value": "#c4c4c4", "inferredRole": "icon" },
        { "name": "color/control/bg/default", "value": "#ffffff", "inferredRole": "background" },
        { "name": "color/control/bg/selected", "value": "#1d6ceb", "inferredRole": "background" },
        { "name": "color/control/bg/selected-alt", "value": "#ffffff", "inferredRole": "background" },
        { "name": "color/control/bg/disabled", "value": "#f5f5f5", "inferredRole": "background" },
        { "name": "color/control/border/selected", "value": "#1d6ceb", "inferredRole": "border" },
        { "name": "color/control/border/default", "value": "#d9d9d9", "inferredRole": "border" },
        { "name": "color/control/border/disabled-alt1", "value": "#d9d9d9", "inferredRole": "border" },
        { "name": "color/blue/50", "value": "#e2f1ff", "inferredRole": "background-range" },
        { "name": "color/base/white", "value": "#ffffff", "inferredRole": "background" },
        { "name": "color/navigation/background", "value": "#ffffff", "inferredRole": "background" },
        { "name": "color/navigation/label/default", "value": "#555555", "inferredRole": "text" },
        { "name": "color/navigation/label/selected", "value": "#1d6ceb", "inferredRole": "text" },
        { "name": "color/navigation/indicator/default", "value": "#d9d9d9", "inferredRole": "border" },
        { "name": "color/navigation/indicator/selected", "value": "#1d6ceb", "inferredRole": "border" },
        { "name": "color/button/bg/primary--default", "value": "#1d6ceb", "inferredRole": "background" },
        { "name": "color/button/border/primary--default", "value": "#1d6ceb", "inferredRole": "border" },
        { "name": "color/button/label/primary--default", "value": "#ffffff", "inferredRole": "text" },
        { "name": "surface/neutral/bg/base", "value": "#ffffff", "inferredRole": "background" },
        { "name": "surface/neutral/bg/subtle", "value": "#f5f5f5", "inferredRole": "background" },
        { "name": "sizing/form-control/height/md", "value": "44", "inferredRole": "sizing" },
        { "name": "sizing/icon/24", "value": "24", "inferredRole": "sizing" },
        { "name": "sizing/24", "value": "24", "inferredRole": "sizing" },
        { "name": "sizing/30", "value": "30", "inferredRole": "sizing" },
        { "name": "sizing/44", "value": "44", "inferredRole": "sizing" },
        { "name": "sizing/56", "value": "56", "inferredRole": "sizing" },
        { "name": "sizing/80", "value": "80", "inferredRole": "sizing" },
        { "name": "radius/full", "value": "999", "inferredRole": "radius" },
        { "name": "radius/4", "value": "4", "inferredRole": "radius" },
        { "name": "border-width/default", "value": "1", "inferredRole": "border-width" },
        { "name": "border-width/100", "value": "1", "inferredRole": "border-width" },
        { "name": "spacing/padding/inline/lg", "value": "24", "inferredRole": "spacing" },
        { "name": "spacing/padding/inline/md", "value": "20", "inferredRole": "spacing" },
        { "name": "spacing/padding/inline/sm", "value": "16", "inferredRole": "spacing" },
        { "name": "spacing/padding/block/md", "value": "20", "inferredRole": "spacing" },
        { "name": "spacing/padding/block/sm", "value": "16", "inferredRole": "spacing" },
        { "name": "spacing/padding/block/xs", "value": "12", "inferredRole": "spacing" },
        { "name": "spacing/section/xs", "value": "16", "inferredRole": "spacing" },
        { "name": "spacing/section/lg", "value": "32", "inferredRole": "spacing" },
        { "name": "spacing/cluster/xs", "value": "12", "inferredRole": "spacing" },
        { "name": "spacing/stack/xs", "value": "12", "inferredRole": "spacing" },
        { "name": "spacing/32", "value": "32", "inferredRole": "spacing" },
        { "name": "title/20B", "value": "Pretendard 20 Bold", "inferredRole": "typography" },
        { "name": "title/24B", "value": "Pretendard 24 Bold", "inferredRole": "typography" },
        { "name": "title/16M", "value": "Pretendard 16 Medium", "inferredRole": "typography" },
        { "name": "title/16B", "value": "Pretendard 16 Bold", "inferredRole": "typography" },
        { "name": "Title/16M", "value": "Pretendard 16 Medium (alias)", "inferredRole": "typography" },
        { "name": "component/button/label/16M", "value": "Pretendard 16 Medium", "inferredRole": "typography" }
      ]
    },
    {
      "nodeId": "540:7663",
      "nodeName": "Style Guide root frame (palette display)",
      "componentRole": "documentation / style guide reference",
      "usedVariables": [
        { "name": "color/text/state/accent-alt", "value": "#ffffff", "inferredRole": "text" },
        { "name": "color/red/300", "value": "#ff4554", "inferredRole": "palette-display" },
        { "name": "color/text/title/primary", "value": "#000000", "inferredRole": "text" },
        { "name": "surface/neutral/bg/subtle", "value": "#f5f5f5", "inferredRole": "background" },
        { "name": "surface/neutral/border/border", "value": "#e9e9e9", "inferredRole": "border" },
        { "name": "surface/base-background/default", "value": "#ffffff", "inferredRole": "background" },
        { "name": "typography/title/base-bold", "value": "Pretendard 18 Bold", "inferredRole": "typography" },
        { "name": "typography/body/base-regular", "value": "Pretendard 18 Regular", "inferredRole": "typography" },
        { "name": "color/brand/look&feel/blue", "value": "#0072ce", "inferredRole": "palette-display" },
        { "name": "color/brand/look&feel/red", "value": "#ff312c", "inferredRole": "palette-display" },
        { "name": "color/brand/look&feel/gray", "value": "#dfdede", "inferredRole": "palette-display" },
        { "name": "color/brand/CI/logo", "value": "#004097", "inferredRole": "palette-display" },
        { "name": "color/base/black", "value": "#000000", "inferredRole": "palette-display" },
        { "name": "color/base/white", "value": "#ffffff", "inferredRole": "palette-display" },
        { "name": "color/blue/50", "value": "#e2f1ff", "inferredRole": "palette-display" },
        { "name": "color/blue/100", "value": "#c8e4ff", "inferredRole": "palette-display" },
        { "name": "color/blue/150", "value": "#a4d4ff", "inferredRole": "palette-display" },
        { "name": "color/blue/200", "value": "#8bc6ff", "inferredRole": "palette-display" },
        { "name": "color/blue/250", "value": "#5bb2ff", "inferredRole": "palette-display" },
        { "name": "color/blue/300", "value": "#2b9eff", "inferredRole": "palette-display" },
        { "name": "color/blue/350", "value": "#268cf8", "inferredRole": "palette-display" },
        { "name": "color/blue/400", "value": "#1d6ceb", "inferredRole": "palette-display" },
        { "name": "color/blue/450", "value": "#2158c8", "inferredRole": "palette-display" },
        { "name": "color/blue/500", "value": "#2747b9", "inferredRole": "palette-display" },
        { "name": "color/gray/0", "value": "#fafafa", "inferredRole": "palette-display" },
        { "name": "color/gray/50", "value": "#f5f5f5", "inferredRole": "palette-display" },
        { "name": "color/gray/100", "value": "#e9e9e9", "inferredRole": "palette-display" },
        { "name": "color/gray/200", "value": "#d9d9d9", "inferredRole": "palette-display" },
        { "name": "color/gray/300", "value": "#c4c4c4", "inferredRole": "palette-display" },
        { "name": "color/gray/400", "value": "#9d9d9d", "inferredRole": "palette-display" },
        { "name": "color/gray/500", "value": "#757575", "inferredRole": "palette-display" },
        { "name": "color/gray/600", "value": "#555555", "inferredRole": "palette-display" },
        { "name": "color/gray/700", "value": "#434343", "inferredRole": "palette-display" },
        { "name": "color/gray/800", "value": "#353535", "inferredRole": "palette-display" },
        { "name": "color/gray/900", "value": "#202020", "inferredRole": "palette-display" },
        { "name": "color/red/50", "value": "#ffebef", "inferredRole": "palette-display" },
        { "name": "color/red/100", "value": "#ffccd6", "inferredRole": "palette-display" },
        { "name": "color/red/150", "value": "#fbb2ba", "inferredRole": "palette-display" },
        { "name": "color/red/200", "value": "#f8979e", "inferredRole": "palette-display" },
        { "name": "color/red/250", "value": "#fc6e79", "inferredRole": "palette-display" },
        { "name": "color/red/350", "value": "#f22544", "inferredRole": "palette-display" },
        { "name": "color/red/400", "value": "#e50533", "inferredRole": "palette-display" },
        { "name": "color/red/450", "value": "#d60228", "inferredRole": "palette-display" },
        { "name": "color/red/500", "value": "#c8001e", "inferredRole": "palette-display" },
        { "name": "color/orange/50", "value": "#ffede0", "inferredRole": "palette-display" },
        { "name": "color/orange/100", "value": "#fdd8bf", "inferredRole": "palette-display" },
        { "name": "color/orange/150", "value": "#fec6a0", "inferredRole": "palette-display" },
        { "name": "color/orange/200", "value": "#ffb482", "inferredRole": "palette-display" },
        { "name": "color/orange/250", "value": "#ff954e", "inferredRole": "palette-display" },
        { "name": "color/orange/300", "value": "#ff761a", "inferredRole": "palette-display" },
        { "name": "color/orange/350", "value": "#ee680d", "inferredRole": "palette-display" },
        { "name": "color/orange/400", "value": "#da4c00", "inferredRole": "palette-display" },
        { "name": "color/orange/450", "value": "#b63c00", "inferredRole": "palette-display" },
        { "name": "color/orange/500", "value": "#8e2e00", "inferredRole": "palette-display" }
      ]
    },
    {
      "nodeId": "540:7368",
      "nodeName": "Typography style frame",
      "componentRole": "typography reference",
      "usedVariables": [
        { "name": "color/text/title/primary", "value": "#000000", "inferredRole": "text" },
        { "name": "color/text/title/secondary", "value": "#353535", "inferredRole": "text" },
        { "name": "color/text/title/tertiary", "value": "#555555", "inferredRole": "text" },
        { "name": "color/text/state/accent-alt", "value": "#ffffff", "inferredRole": "text" },
        { "name": "color/icon/red", "value": "#ff4554", "inferredRole": "icon" },
        { "name": "color/line/gray/default", "value": "#d9d9d9", "inferredRole": "border" },
        { "name": "surface/neutral/bg/subtle", "value": "#f5f5f5", "inferredRole": "background" },
        { "name": "surface/neutral/border/border", "value": "#e9e9e9", "inferredRole": "border" },
        { "name": "surface/base-background/default", "value": "#ffffff", "inferredRole": "background" },
        { "name": "Title/18M", "value": "Pretendard 18 Medium", "inferredRole": "typography" },
        { "name": "title/32B", "value": "Pretendard 32 Bold", "inferredRole": "typography" },
        { "name": "radius/4", "value": "4", "inferredRole": "radius" }
      ]
    }
  ],
  "variableUsage": [
    { "variableName": "color/form-control/bg/default", "value": "#ffffff", "usageCount": 2, "usedInComponents": ["540:3794", "6456:4033"], "inferredRoles": ["background"], "scope": "form-control (semantic)" },
    { "variableName": "color/form-control/bg/disabled", "value": "#f5f5f5", "usageCount": 2, "usedInComponents": ["540:3794", "6456:4033"], "inferredRoles": ["background"], "scope": "form-control (semantic)" },
    { "variableName": "color/form-control/border/default", "value": "#d9d9d9", "usageCount": 2, "usedInComponents": ["540:3794", "6456:4033"], "inferredRoles": ["border"], "scope": "form-control (semantic)" },
    { "variableName": "color/form-control/border/selected", "value": "#1d6ceb", "usageCount": 2, "usedInComponents": ["540:3794", "6456:4033"], "inferredRoles": ["border"], "scope": "form-control (semantic)" },
    { "variableName": "color/form-control/border/disabled", "value": "#d9d9d9", "usageCount": 2, "usedInComponents": ["540:3794", "6456:4033"], "inferredRoles": ["border"], "scope": "form-control (semantic)" },
    { "variableName": "color/form-control/text/default", "value": "#353535", "usageCount": 2, "usedInComponents": ["540:3794", "6456:4033"], "inferredRoles": ["text"], "scope": "form-control (semantic)" },
    { "variableName": "color/form-control/text/placeholder", "value": "#757575", "usageCount": 2, "usedInComponents": ["540:3794", "6456:4033"], "inferredRoles": ["text"], "scope": "form-control (semantic)" },
    { "variableName": "color/form-control/text/disabled", "value": "#c4c4c4", "usageCount": 2, "usedInComponents": ["540:3794", "6456:4033"], "inferredRoles": ["text"], "scope": "form-control (semantic)" },
    { "variableName": "color/button/bg/primary--default", "value": "#1d6ceb", "usageCount": 3, "usedInComponents": ["540:4501", "540:3836", "6456:4033"], "inferredRoles": ["background"], "scope": "button component-alias" },
    { "variableName": "color/button/border/primary--default", "value": "#1d6ceb", "usageCount": 3, "usedInComponents": ["540:4501", "540:3836", "6456:4033"], "inferredRoles": ["border"], "scope": "button component-alias" },
    { "variableName": "color/button/label/primary--default", "value": "#ffffff", "usageCount": 4, "usedInComponents": ["540:4501", "540:4502", "540:3836", "6456:4033"], "inferredRoles": ["text"], "scope": "button component-alias" },
    { "variableName": "color/text/title/primary", "value": "#000000", "usageCount": 4, "usedInComponents": ["540:3836", "6456:4033", "540:7663", "540:7368"], "inferredRoles": ["text"], "scope": "text semantic" },
    { "variableName": "color/text/title/secondary", "value": "#353535", "usageCount": 1, "usedInComponents": ["540:7368"], "inferredRoles": ["text"], "scope": "text semantic" },
    { "variableName": "color/text/title/tertiary", "value": "#555555", "usageCount": 1, "usedInComponents": ["540:7368"], "inferredRoles": ["text"], "scope": "text semantic" },
    { "variableName": "color/text/body/primary", "value": "#353535", "usageCount": 2, "usedInComponents": ["540:3836", "6456:4033"], "inferredRoles": ["text"], "scope": "text semantic" },
    { "variableName": "color/text/body/tertiary", "value": "#757575", "usageCount": 2, "usedInComponents": ["540:3836", "6456:4033"], "inferredRoles": ["text"], "scope": "text semantic" },
    { "variableName": "color/text/state/disabled", "value": "#c4c4c4", "usageCount": 2, "usedInComponents": ["540:3836", "6456:4033"], "inferredRoles": ["text"], "scope": "text state semantic" },
    { "variableName": "color/text/state/accent", "value": "#1d6ceb", "usageCount": 2, "usedInComponents": ["540:3836", "6456:4033"], "inferredRoles": ["text"], "scope": "text state semantic" },
    { "variableName": "color/text/state/accent-alt", "value": "#ffffff", "usageCount": 5, "usedInComponents": ["540:3836", "6456:4033", "540:7663", "540:7665", "540:7368"], "inferredRoles": ["text"], "scope": "text state semantic" },
    { "variableName": "color/icon/gray-dark", "value": "#353535", "usageCount": 3, "usedInComponents": ["540:3794", "540:3836", "6456:4033"], "inferredRoles": ["icon"], "scope": "icon semantic" },
    { "variableName": "color/icon/gray-light", "value": "#c4c4c4", "usageCount": 2, "usedInComponents": ["540:3794", "6456:4033"], "inferredRoles": ["icon"], "scope": "icon semantic" },
    { "variableName": "color/icon/red", "value": "#ff4554", "usageCount": 1, "usedInComponents": ["540:7368"], "inferredRoles": ["icon"], "scope": "icon semantic" },
    { "variableName": "color/control/bg/default", "value": "#ffffff", "usageCount": 2, "usedInComponents": ["540:3836", "6456:4033"], "inferredRoles": ["background"], "scope": "control semantic (day-cell, etc.)" },
    { "variableName": "color/control/bg/selected", "value": "#1d6ceb", "usageCount": 2, "usedInComponents": ["540:3836", "6456:4033"], "inferredRoles": ["background"], "scope": "control semantic" },
    { "variableName": "color/control/bg/selected-alt", "value": "#ffffff", "usageCount": 2, "usedInComponents": ["540:3836", "6456:4033"], "inferredRoles": ["background"], "scope": "control semantic" },
    { "variableName": "color/control/bg/disabled", "value": "#f5f5f5", "usageCount": 1, "usedInComponents": ["6456:4033"], "inferredRoles": ["background"], "scope": "control semantic" },
    { "variableName": "color/control/border/selected", "value": "#1d6ceb", "usageCount": 2, "usedInComponents": ["540:3836", "6456:4033"], "inferredRoles": ["border"], "scope": "control semantic" },
    { "variableName": "color/control/border/default", "value": "#d9d9d9", "usageCount": 1, "usedInComponents": ["6456:4033"], "inferredRoles": ["border"], "scope": "control semantic" },
    { "variableName": "color/control/border/disabled-alt1", "value": "#d9d9d9", "usageCount": 1, "usedInComponents": ["6456:4033"], "inferredRoles": ["border"], "scope": "control semantic" },
    { "variableName": "color/navigation/background", "value": "#ffffff", "usageCount": 1, "usedInComponents": ["6456:4033"], "inferredRoles": ["background"], "scope": "navigation component-alias" },
    { "variableName": "color/navigation/label/default", "value": "#555555", "usageCount": 1, "usedInComponents": ["6456:4033"], "inferredRoles": ["text"], "scope": "navigation component-alias" },
    { "variableName": "color/navigation/label/selected", "value": "#1d6ceb", "usageCount": 1, "usedInComponents": ["6456:4033"], "inferredRoles": ["text"], "scope": "navigation component-alias" },
    { "variableName": "color/navigation/indicator/default", "value": "#d9d9d9", "usageCount": 1, "usedInComponents": ["6456:4033"], "inferredRoles": ["border"], "scope": "navigation component-alias" },
    { "variableName": "color/navigation/indicator/selected", "value": "#1d6ceb", "usageCount": 1, "usedInComponents": ["6456:4033"], "inferredRoles": ["border"], "scope": "navigation component-alias" },
    { "variableName": "color/line/gray/default", "value": "#d9d9d9", "usageCount": 1, "usedInComponents": ["540:7368"], "inferredRoles": ["border"], "scope": "border semantic" },
    { "variableName": "color/base/white", "value": "#ffffff", "usageCount": 3, "usedInComponents": ["540:3836", "6456:4033", "540:7663"], "inferredRoles": ["background", "palette-display"], "scope": "foundation base" },
    { "variableName": "color/base/black", "value": "#000000", "usageCount": 1, "usedInComponents": ["540:7663"], "inferredRoles": ["palette-display"], "scope": "foundation base" },
    { "variableName": "color/blue/50", "value": "#e2f1ff", "usageCount": 3, "usedInComponents": ["540:3836", "6456:4033", "540:7663"], "inferredRoles": ["background-range", "palette-display"], "scope": "foundation palette" },
    { "variableName": "color/red/300", "value": "#ff4554", "usageCount": 2, "usedInComponents": ["540:7663", "540:7665"], "inferredRoles": ["palette-display"], "scope": "foundation palette" },
    { "variableName": "surface/base-background/default", "value": "#ffffff", "usageCount": 2, "usedInComponents": ["540:7663", "540:7368"], "inferredRoles": ["background"], "scope": "surface semantic" },
    { "variableName": "surface/neutral/bg/base", "value": "#ffffff", "usageCount": 2, "usedInComponents": ["540:3836", "6456:4033"], "inferredRoles": ["background"], "scope": "surface semantic" },
    { "variableName": "surface/neutral/bg/subtle", "value": "#f5f5f5", "usageCount": 3, "usedInComponents": ["6456:4033", "540:7663", "540:7368"], "inferredRoles": ["background"], "scope": "surface semantic" },
    { "variableName": "surface/neutral/border/border", "value": "#e9e9e9", "usageCount": 2, "usedInComponents": ["540:7663", "540:7368"], "inferredRoles": ["border"], "scope": "surface semantic" },
    { "variableName": "color/brand/look&feel/blue", "value": "#0072ce", "usageCount": 1, "usedInComponents": ["540:7663"], "inferredRoles": ["palette-display"], "scope": "brand reference" },
    { "variableName": "color/brand/look&feel/red", "value": "#ff312c", "usageCount": 1, "usedInComponents": ["540:7663"], "inferredRoles": ["palette-display"], "scope": "brand reference" },
    { "variableName": "color/brand/look&feel/gray", "value": "#dfdede", "usageCount": 1, "usedInComponents": ["540:7663"], "inferredRoles": ["palette-display"], "scope": "brand reference" },
    { "variableName": "color/brand/CI/logo", "value": "#004097", "usageCount": 1, "usedInComponents": ["540:7663"], "inferredRoles": ["palette-display"], "scope": "brand reference" },
    { "variableName": "sizing/form-control/height/md", "value": "44", "usageCount": 2, "usedInComponents": ["540:3794", "6456:4033"], "inferredRoles": ["sizing"], "scope": "form-control sizing" },
    { "variableName": "sizing/form-control/height/lg", "value": "48", "usageCount": 1, "usedInComponents": ["540:3794"], "inferredRoles": ["sizing"], "scope": "form-control sizing" },
    { "variableName": "sizing/form-control/height/xs", "value": "34", "usageCount": 1, "usedInComponents": ["540:3794"], "inferredRoles": ["sizing"], "scope": "form-control sizing" },
    { "variableName": "sizing/form-control/height/xxs", "value": "28", "usageCount": 1, "usedInComponents": ["540:3794"], "inferredRoles": ["sizing"], "scope": "form-control sizing" },
    { "variableName": "sizing/button/height/md", "value": "44", "usageCount": 1, "usedInComponents": ["540:4501"], "inferredRoles": ["sizing"], "scope": "button sizing" },
    { "variableName": "sizing/icon/24", "value": "24", "usageCount": 2, "usedInComponents": ["540:3836", "6456:4033"], "inferredRoles": ["sizing"], "scope": "icon sizing" },
    { "variableName": "radius/4", "value": "4", "usageCount": 5, "usedInComponents": ["540:3794", "540:4501", "540:3836", "6456:4033", "540:7368"], "inferredRoles": ["radius"], "scope": "foundation radius" },
    { "variableName": "radius/control/sm", "value": "4", "usageCount": 1, "usedInComponents": ["540:3794"], "inferredRoles": ["radius"], "scope": "control semantic radius" },
    { "variableName": "radius/full", "value": "999", "usageCount": 2, "usedInComponents": ["540:3836", "6456:4033"], "inferredRoles": ["radius"], "scope": "foundation radius" },
    { "variableName": "border-width/default", "value": "1", "usageCount": 4, "usedInComponents": ["540:3794", "540:4501", "540:3836", "6456:4033"], "inferredRoles": ["border-width"], "scope": "foundation border-width" },
    { "variableName": "border-width/100", "value": "1", "usageCount": 2, "usedInComponents": ["540:3836", "6456:4033"], "inferredRoles": ["border-width"], "scope": "foundation border-width" }
  ],
  "unusedVariables": [
    { "variableName": "color/orange/* (50~500)", "reason": "scanned components do not use orange palette; appears only on palette display frame 540:7663", "recommendation": "stable, keep — referenced for palette documentation only" }
  ],
  "needsReview": [
    { "issue": "border-width/default vs border-width/100", "reason": "both resolve to 1, both used by button + datepicker mobile + datepicker section 2", "recommendation": "consolidate to single variable (legacy duplication suspected)" },
    { "issue": "radius/4 vs radius/control/sm", "reason": "both resolve to 4, both used by datepicker_input (540:3794)", "recommendation": "decide which is canonical — likely keep radius/control/sm as semantic" },
    { "issue": "title/16M vs Title/16M", "reason": "case-only variant — both used by datepicker mobile + section 2", "recommendation": "duplicate Variable name with different case — likely accidental, deprecate one" },
    { "issue": "color/control/bg/disabled vs color/form-control/bg/disabled", "reason": "both resolve #f5f5f5; control used in DatePicker section 2 (6456:4033), form-control used in datepicker_input (540:3794) and section 2", "recommendation": "control and form-control are distinct semantic scopes; verify intended split (control = generic, form-control = input/select/datepicker trigger)" },
    { "issue": "color/control/border/default vs color/control/border/disabled-alt1", "reason": "both resolve #d9d9d9; -alt1 suffix suggests legacy variant", "recommendation": "verify -alt1 is still needed — likely deprecated" },
    { "issue": "color/text/state/accent-alt = #ffffff", "reason": "uses 'accent-alt' name but value is white; usage confirms it is text-on-accent (label on selected day cell)", "recommendation": "rename to color/text/on-accent or color/text/state/inverse" },
    { "issue": "MCP access failed: 6443:4408 (Login input), 6443:4655 (DatePicker), 6443:4606 (TimePicker)", "reason": "Figma MCP returns invalid node — likely moved or restructured", "recommendation": "Figma 직접 확인 후 nodeId 재등록 필요 (registry/figma/figma-map.json)" }
  ]
}
